py.typed
friendliai/__init__.py
friendliai/_hooks/__init__.py
friendliai/_hooks/registration.py
friendliai/_hooks/sdkhooks.py
friendliai/_hooks/types.py
friendliai/_version.py
friendliai/basesdk.py
friendliai/httpclient.py
friendliai/inference.py
friendliai/models/__init__.py
friendliai/models/assistantmessage.py
friendliai/models/chatcompletionchoice.py
friendliai/models/chatcompletionop.py
friendliai/models/chatcompletionrequestbody.py
friendliai/models/chatcompletionresponse.py
friendliai/models/completionchoice.py
friendliai/models/completionop.py
friendliai/models/completionrequestbody.py
friendliai/models/completionrequestbodywithprompt.py
friendliai/models/completionrequestbodywithtokens.py
friendliai/models/completionresponse.py
friendliai/models/detokenizationop.py
friendliai/models/detokenizationrequestbody.py
friendliai/models/detokenizationresponse.py
friendliai/models/filebuiltintool.py
friendliai/models/function.py
friendliai/models/functiontool.py
friendliai/models/logprobs.py
friendliai/models/message.py
friendliai/models/otherbuiltintool.py
friendliai/models/sdkerror.py
friendliai/models/security.py
friendliai/models/streamedchatcompletionchoice.py
friendliai/models/streamedchatcompletionresponse.py
friendliai/models/streamedcompletionresponse.py
friendliai/models/streamedcompletiontokencomplete.py
friendliai/models/streamedcompletiontokensampled.py
friendliai/models/streamedtoolassistedchatcompletionresponse.py
friendliai/models/systemmessage.py
friendliai/models/textresponseformat.py
friendliai/models/tokenizationop.py
friendliai/models/tokenizationrequestbody.py
friendliai/models/tokenizationresponse.py
friendliai/models/tokensequence.py
friendliai/models/tool.py
friendliai/models/toolassistedchatcompletionop.py
friendliai/models/toolassistedcompletionrequestbody.py
friendliai/models/toolfortoolassistedchat.py
friendliai/models/toolmessage.py
friendliai/models/usage.py
friendliai/models/usermessage.py
friendliai/py.typed
friendliai/sdk.py
friendliai-0.1.1.dist-info/METADATA
friendliai-0.1.1.dist-info/WHEEL
friendliai-0.1.1.dist-info/RECORD
